pyknowsis/__init__.py
pyknowsis-0.1.6.dist-info/DESCRIPTION.rst
pyknowsis-0.1.6.dist-info/METADATA
pyknowsis-0.1.6.dist-info/RECORD
pyknowsis-0.1.6.dist-info/WHEEL
pyknowsis-0.1.6.dist-info/metadata.json
pyknowsis-0.1.6.dist-info/top_level.txt
tests/__init__.py
tests/api_tests.py
