Metadata-Version: 2.0
Name: pyknowsis
Version: 0.1.6
Summary: API Wrapper for the Knowsis API
Home-page: https://github.com/knowsis/pyknowsis
Author: Knowsis Ltd
Author-email: mark@knowsis.com
License: UNKNOWN
Download-URL: https://github.com/knowsis/pyknowsis/tarball/0.1.5
Platform: UNKNOWN
Requires-Dist: oauth2
Requires-Dist: python-dateutil
Requires-Dist: requests
Requires-Dist: simplejson
